{
  "runAt": "2026-07-01 19:22:27",
  "sections": {
    "domestic": {
      "before": 47,
      "after": 47,
      "duplicates": 0,
      "authoritativeTop10": 9
    },
    "international": {
      "before": 78,
      "after": 78,
      "duplicates": 0,
      "authoritativeTop10": 1
    },
    "ai": {
      "before": 80,
      "after": 80,
      "duplicates": 0,
      "authoritativeTop10": 0
    },
    "entertainment": {
      "before": 15,
      "after": 15,
      "duplicates": 0,
      "authoritativeTop10": 2
    },
    "stock": {
      "before": 80,
      "after": 80,
      "duplicates": 0,
      "authoritativeTop10": 0
    },
    "henan": {
      "before": 6,
      "after": 6,
      "duplicates": 0,
      "authoritativeTop10": 0
    },
    "csl": {
      "before": 7,
      "after": 7,
      "duplicates": 0,
      "authoritativeTop10": 0
    }
  },
  "duplicateMerged": 0,
  "domesticHighPoliticsTop8": 8,
  "changedArrays": {
    "generated_news_arrays.js": [
      "mockHotNewsDomestic",
      "mockHotNewsDomesticExtra",
      "mockHotNewsInternational",
      "mockHotNewsInternationalExtra",
      "mockHotNewsAI",
      "mockHotNewsAIExtra",
      "mockEntertainment",
      "mockEntertainmentExtra",
      "mockStockNews",
      "mockStockNewsExtra",
      "mockHenanNews",
      "mockCslOtherTeams"
    ],
    "index.html": [
      "mockHotNewsDomestic",
      "mockHotNewsDomesticExtra",
      "mockHotNewsInternational",
      "mockHotNewsInternationalExtra",
      "mockHotNewsAI",
      "mockHotNewsAIExtra",
      "mockEntertainment",
      "mockEntertainmentExtra",
      "mockStockNews",
      "mockStockNewsExtra",
      "mockHenanNews",
      "mockCslOtherTeams"
    ]
  }
}